armcnc/__init__.py
armcnc/config/__init__.py
armcnc/machine/__init__.py
armcnc/machine/command.py
armcnc/machine/error.py
armcnc/service/__init__.py
armcnc/utils/__init__.py
armcnc/utils/loging/__init__.py
armcnc-2.1.7.dist-info/METADATA
armcnc-2.1.7.dist-info/WHEEL
armcnc-2.1.7.dist-info/top_level.txt
armcnc-2.1.7.dist-info/RECORD
