Metadata-Version: 2.1
Name: armcnc
Version: 2.1.7
Summary: Python development framework for armcnc.
Home-page: https://github.com/armcnc/armcnc
Author: MakerYang
Author-email: admin@wileho.com
License: Apache-2.0
Project-URL: Documentation, https://www.armcnc.net
Project-URL: Website, https://armcnc.net
Project-URL: Source, https://github.com/armcnc/armcnc
Keywords: armcnc,cnc,arm64,arm,linuxcnc,ubuntu
Classifier: Intended Audience :: Developers
Classifier: License :: OSI Approved :: Apache Software License
Classifier: Topic :: Multimedia :: Sound/Audio
Classifier: Topic :: Multimedia :: Video
Classifier: Topic :: Scientific/Engineering :: Artificial Intelligence
Classifier: Programming Language :: Python :: 3
Classifier: Programming Language :: Python :: 3.9
Classifier: Programming Language :: Python :: 3.10
Classifier: Programming Language :: Python :: 3 :: Only
Requires-Python: >=3.9.0
Requires-Dist: requests>=2.32.3
